axolpy/bitbucket/__init__.py
axolpy/configuration/__init__.py
axolpy/kubernetes/__init__.py
axolpy/logging/__init__.py
axolpy/solidity/__init__.py
axolpy/util/__init__.py
axolpy/util/types.py
axolpy/util/collectionfunctions/__init__.py
axolpy/util/helper/__init__.py
axolpy/util/helper/string.py
axolpy_lib-1.1.0.dist-info/LICENSE.md
axolpy_lib-1.1.0.dist-info/METADATA
axolpy_lib-1.1.0.dist-info/WHEEL
axolpy_lib-1.1.0.dist-info/top_level.txt
axolpy_lib-1.1.0.dist-info/RECORD
