Metadata-Version: 2.1
Name: axolpy-lib
Version: 1.1.0
Summary: Axolotl Library in Python
Author-email: tchiunam <tchiunam@gmail.com>
License: MIT License        
Project-URL: homepage, https://github.com/tchiunam/axolpy-lib
Project-URL: repository, https://github.com/tchiunam/axolpy-lib
Project-URL: documentation, https://github.com/tchiunam/axolpy-lib
Keywords: axolotl
Classifier: Development Status :: 5 - Production/Stable
Classifier: License :: OSI Approved :: MIT License
Classifier: Natural Language :: English
Classifier: Operating System :: OS Independent
Classifier: Programming Language :: Python :: 3
Classifier: Topic :: Software Development :: Libraries :: Python Modules
Classifier: Topic :: Utilities
Requires-Python: >=3.7
License-File: LICENSE.md
Requires-Dist: coloredlogs
Provides-Extra: atlassian
Requires-Dist: atlassian-python-api ; extra == 'atlassian'
Provides-Extra: web3
Requires-Dist: py-solc-x ; extra == 'web3'
